pytest_mongodb_ry/__init__.py
pytest_mongodb_ry/plugin.py
pytest_mongodb_nono-0.0.0.dist-info/METADATA
pytest_mongodb_nono-0.0.0.dist-info/WHEEL
pytest_mongodb_nono-0.0.0.dist-info/entry_points.txt
pytest_mongodb_nono-0.0.0.dist-info/top_level.txt
pytest_mongodb_nono-0.0.0.dist-info/RECORD
