Metadata-Version: 2.1
Name: pytest-mongodb-nono
Version: 0.0.0
Summary: pytest plugin for MongoDB 
Author-email: Xue hy <ryhn0412@163.com>, Yan yp <18065786386@163.com>
Classifier: Programming Language :: Python
Classifier: Programming Language :: Python :: 3
Classifier: Framework :: Pytest
Classifier: Topic :: Database
Classifier: Topic :: Software Development :: Libraries
Requires-Dist: pymongo
